simba/__init__.py
simba/base_functions.py
simba/dotexprs_reader_printer.py
simba/emitter.py
simba/helpers.py
simba/rubbish.py
simba/sexprs_reader_printer.py
simba/simba.py
simba/simba_exceptions.py
simba/simba_types.py
simba/simplest_test_suite.py
simba/test_runner.py
simba/sb/__init__.py
simba/sb/base.sb
simba/sb/combinators.sb
simba/sb/examples.sb
simba_lang-0.1.10.dist-info/LICENSE
simba_lang-0.1.10.dist-info/METADATA
simba_lang-0.1.10.dist-info/WHEEL
simba_lang-0.1.10.dist-info/entry_points.txt
simba_lang-0.1.10.dist-info/top_level.txt
simba_lang-0.1.10.dist-info/RECORD
