Metadata-Version: 2.1
Name: simba-lang
Version: 0.1.10
Summary: The Simba programming language
Author: Jérémie Vaney
Author-email: jeremievaney@gmail.com
License: MIT
Platform: UNKNOWN
Classifier: Programming Language :: Python :: 3
Classifier: License :: OSI Approved :: MIT License
Classifier: Operating System :: OS Independent
Requires-Python: >=3.6
License-File: LICENSE
Requires-Dist: pyrsistent
Requires-Dist: prompt-toolkit
Requires-Dist: toolz
